kiro_gateway/__init__.py
kiro_gateway/auth.py
kiro_gateway/cache.py
kiro_gateway/config.py
kiro_gateway/converters.py
kiro_gateway/debug_logger.py
kiro_gateway/exceptions.py
kiro_gateway/http_client.py
kiro_gateway/main.py
kiro_gateway/models.py
kiro_gateway/parsers.py
kiro_gateway/routes.py
kiro_gateway/streaming.py
kiro_gateway/tokenizer.py
kiro_gateway/utils.py
kiro_openai_gateway-1.0.9.dist-info/LICENSE
kiro_openai_gateway-1.0.9.dist-info/METADATA
kiro_openai_gateway-1.0.9.dist-info/WHEEL
kiro_openai_gateway-1.0.9.dist-info/entry_points.txt
kiro_openai_gateway-1.0.9.dist-info/RECORD
