Metadata-Version: 2.3
Name: kiro-openai-gateway
Version: 1.0.9
Summary: OpenAI-compatible proxy gateway for Kiro IDE API (AWS CodeWhisperer)
License: AGPL-3.0
Author: Jwadow
Requires-Python: >=3.10,<4.0
Classifier: License :: OSI Approved :: GNU Affero General Public License v3
Classifier: Programming Language :: Python :: 3
Classifier: Programming Language :: Python :: 3.10
Classifier: Programming Language :: Python :: 3.11
Classifier: Programming Language :: Python :: 3.12
Classifier: Programming Language :: Python :: 3.13
Requires-Dist: fastapi (>=0.100.0,<0.101.0)
Requires-Dist: httpx (>=0.27.0,<0.28.0)
Requires-Dist: loguru (>=0.7.0,<0.8.0)
Requires-Dist: python-dotenv (>=1.0.0,<2.0.0)
Requires-Dist: requests (>=2.31.0,<3.0.0)
Requires-Dist: tiktoken (>=0.8.0,<0.9.0)
Requires-Dist: uvicorn[standard] (>=0.30.0,<0.31.0)
Project-URL: Repository, https://github.com/Jwadow/kiro-openai-gateway
